lab3/booth_extra/booth2.v
module booth2 (
    input  wire        clk  ,
	input  wire        rst_n,
	input  wire [15:0] x    ,
	input  wire [15:0] y    ,
	input  wire        start,
	output reg [31:0] z    ,
	output wire        busy 
);

//double signed bit
reg [31:0]	x_reg;
reg [31:0]	x_reg_neg;

reg [15:0]	x_reg_double_temp;
reg [15:0]	x_reg_neg_double_temp;
reg [31:0]	x_reg_double;
reg [31:0]	x_reg_neg_double;

reg [0:16]	y_reg;
reg [31:0]	z_temp;

reg			busy_flag;
reg	[31:0]	times;

assign busy = busy_flag;

//Initialize and assign the regs
always @(posedge clk or negedge rst_n) begin
	if(~rst_n) begin
		x_reg <= 0;
		x_reg_neg <= 0;
		x_reg_double <= 0;
		x_reg_neg_double <= 0;
		y_reg <= {16'h0000,1'b0};
		busy_flag <= 0;
	end

	else if(start) begin
		x_reg <= {x,16'h0000};
		x_reg_neg <= (~x + 1) << 16;
		y_reg <= {y,1'b0};
		busy_flag <= 1;

		x_reg_double_temp = x + x;
		x_reg_neg_double_temp = (~x+1) + (~x+1);

		x_reg_double = {x_reg_double_temp, 16'h0000};
		x_reg_neg_double = {x_reg_neg_double_temp, 16'h0000};
	end
end



//Start computing
always @(posedge clk or negedge rst_n) begin
	if(~rst_n) begin
		times <= 0;
		z_temp <= 0;
	end
	if(start)	begin
		times <= 0;
		z_temp <= 0;
	end
	if(busy_flag) begin
		if(times > 8) begin
			z <= z_temp;
			busy_flag <= 0;
		end

		else if(times == 8) begin
				case (y_reg[14:16])
				000:	begin
				end 
				001:	begin
					z_temp = z_temp + x_reg;
				end
				010:	begin
					z_temp = z_temp + x_reg;
				end
				011:	begin
					z_temp = z_temp + x_reg + x_reg;
				end
				100:	begin
					z_temp = z_temp + x_reg_neg + x_reg_neg;
				end
				101:	begin
					z_temp = z_temp + x_reg_neg;
				end
				110:		begin
					z_temp = z_temp + x_reg_neg;
				end
				111:		begin
				end
				default: z_temp <= z_temp;
			endcase
		end

		else begin
			case (y_reg[14:16])
				000:	begin
					z_temp <= {{2{z_temp[31]}}, z_temp[31:2]};
				end 
				001:	begin
					z_temp = z_temp + x_reg;
					z_temp = {{2{z_temp[31]}}, z_temp[31:2]};
				end
				010:	begin
					z_temp = z_temp + x_reg;
					z_temp = {{2{z_temp[31]}}, z_temp[31:2]};
				end
				011:	begin
					z_temp = z_temp + x_reg + x_reg;
					z_temp = {{2{z_temp[31]}}, z_temp[31:2]};
				end
				100:	begin
					z_temp = z_temp + x_reg_neg + x_reg_neg;
					z_temp = {{2{z_temp[31]}}, z_temp[31:2]};					
				end
				101:	begin
					z_temp = z_temp + x_reg_neg;
					z_temp = {{2{z_temp[31]}}, z_temp[31:2]};						
				end
				110:		begin
					z_temp = z_temp + x_reg_neg;
					z_temp = {{2{z_temp[31]}}, z_temp[31:2]};
				end
				111:		begin
					z_temp <= {{2{z_temp[31]}}, z_temp[31:2]};					
				end
				default: z_temp <= z_temp;
			endcase
		end

		y_reg <= y_reg >> 3;
		times <= times + 1;
	end

end


endmodule

lab3/booth_extra/testbench.v
`timescale 1ns/1ps

module testbench(
);

reg clk  ;
reg rst_n;
reg start; 
wire busy ;

reg  [15:0] x;
reg  [15:0] y;
wire [31:0] z;

reg        wrong        ;
reg [31:0] result [8:0] ;

initial begin
	$dumpfile("booth2.vcd");
	$dumpvars(0,testbench);
    clk = 0;
    rst_n = 0;
    start = 0;
    #12;
    rst_n = 1;
    start = 1;
    #200
    start = 0;
    #2000;
    $finish;

end

always #5 clk = ~clk;

reg start_ff;
reg start_ff2;
reg start_ff3;
reg start_r_ff;

reg [3:0] test_cnt1  ;
reg [4:0] test_cnt2  ;
reg       test_period;

always @ (posedge clk or negedge rst_n) begin
    if (~rst_n) start_ff <= 1'b0;
    else        start_ff <= start;
end

always @ (posedge clk or negedge rst_n) begin
    if (~rst_n) start_ff2 <= 1'b0;
    else        start_ff2 <= start_ff;
end

always @ (posedge clk or negedge rst_n) begin
    if (~rst_n) start_ff3 <= 1'b0;
    else        start_ff3 <= start_ff2;
end

wire start_r = start_ff2 & ~start_ff3;

always @ (posedge clk or negedge rst_n) begin
    if (~rst_n) start_r_ff <= 1'b0;
    else        start_r_ff <= (test_cnt2 == 5'h01) & test_period;
end

wire test_cnt1_end = (test_cnt1 == 4'h8) & test_cnt2_end;
wire test_cnt2_end = (test_cnt2 == 5'hD);
wire check_point = (test_cnt2 == 5'hC);

always @ (posedge clk or negedge rst_n) begin
    if (~rst_n)             test_period <= 1'b0;
	else if (test_cnt1_end) test_period <= 1'b0;
	else if (start_r)       test_period <= 1'b1;
end

always @ (posedge clk or negedge rst_n) begin
    if (~rst_n)             test_cnt1 <= 4'h0;
	else if (test_cnt1_end) test_cnt1 <= 4'h0;
	else if (test_cnt2_end) test_cnt1 <= test_cnt1 + 4'h1;
end

always @ (posedge clk or negedge rst_n) begin
    if (~rst_n)             test_cnt2 <= 5'h00;
	else if (test_cnt2_end) test_cnt2 <= 5'h00;
	else if (test_period)   test_cnt2 <= test_cnt2 + 5'h01;
end

wire test_cnt2_eq_1 = (test_cnt2 == 5'h01);

always @ (posedge clk or negedge rst_n) begin
    if (~rst_n) x <= 16'h0;
	else if (test_cnt2_eq_1) begin
	    case (test_cnt1)
		    4'h0 : x <= 16'h0006;
			4'h1 : x <= 16'hfffa;
			4'h2 : x <= 16'h0000;
			4'h3 : x <= 16'h1234;
			4'h4 : x <= 16'hf100;
			4'h5 : x <= 16'h8001;
			4'h6 : x <= 16'h7658;
			4'h7 : x <= 16'h04f8;
			4'h8 : x <= 16'h0589;
			default : x <= 16'h0;
		endcase
	end
	else x <= 16'h0;
end

always @ (posedge clk or negedge rst_n) begin
    if (~rst_n) y <= 16'h0;
	else if (test_cnt2_eq_1) begin
	    case (test_cnt1)
		    4'h0 : y <= 16'h0005;
			4'h1 : y <= 16'h0005;
			4'h2 : y <= 16'hff21;
			4'h3 : y <= 16'h1234;
			4'h4 : y <= 16'hf789;
			4'h5 : y <= 16'h6578;
			4'h6 : y <= 16'h0000;
			4'h7 : y <= 16'h1400;
			4'h8 : y <= 16'hc643;
			default : y <= 16'h0;
		endcase
	end
	else y <= 16'h0;
end

integer i;
always @ (posedge clk or negedge rst_n) begin
    if (~rst_n) begin
	    for (i=0;i<=7;i=i+1)
		   result[i] <= 32'h0;
	end
	else begin
		result[0] <= 32'h0000001e;
		result[1] <= 32'hffffffe2;
		result[2] <= 32'h00000000;
		result[3] <= 32'h014B5A90;
		result[4] <= 32'h007EF900;
		result[5] <= 32'hCD446578;
		result[6] <= 32'h00000000;
		result[7] <= 32'h00636000;
		result[8] <= 32'hFEC068DB;
	end
end

always @ (posedge clk or negedge rst_n) begin
    if (~rst_n) wrong <= 1'b0;
	else if (check_point) begin
		wrong <= ~(result[test_cnt1] == z);
    end
end	

always @ (posedge clk) begin
	if (wrong) begin
	    $display("wrong at index %x",test_cnt1);
	    $display("=====================================");
	    $display("Test end!");
        $display("----FAIL!!!");
		$display("x           : %x",x);
		$display("y           : %x",y);
		$display("reference   : %x",result[test_cnt1]);
		$display("test module : %x",z); 
	    $finish;
    end
	else if (test_cnt1_end) begin
	    $display("test %x finished",test_cnt1);
	    $display("====================================");
	    $display("Test end!");
        $display("----PASS!!!");
	    $finish;
    end
end

booth2 u_booth2 (
    .clk    (clk       ),
    .rst_n  (rst_n     ),
    .x      (x         ),
    .y      (y         ),
    .start  (start_r_ff),
    .z      (z         ),
    .busy   (busy      )
);

endmodule

lab3/booth_extra/booth2.vcd
$date
	Wed May 18 19:44:43 2022
$end
$version
	Icarus Verilog
$end
$timescale
	1ps
$end
$scope module testbench $end
$var wire 1 ! start_r $end
$var wire 1 " test_cnt1_end $end
$var wire 32 # z [31:0] $end
$var wire 1 $ test_cnt2_eq_1 $end
$var wire 1 % test_cnt2_end $end
$var wire 1 & check_point $end
$var wire 1 ' busy $end
$var reg 1 ( clk $end
$var reg 1 ) rst_n $end
$var reg 1 * start $end
$var reg 1 + start_ff $end
$var reg 1 , start_ff2 $end
$var reg 1 - start_ff3 $end
$var reg 1 . start_r_ff $end
$var reg 4 / test_cnt1 [3:0] $end
$var reg 5 0 test_cnt2 [4:0] $end
$var reg 1 1 test_period $end
$var reg 1 2 wrong $end
$var reg 16 3 x [15:0] $end
$var reg 16 4 y [15:0] $end
$var integer 32 5 i [31:0] $end
$scope module u_booth2 $end
$var wire 1 ' busy $end
$var wire 1 ( clk $end
$var wire 1 ) rst_n $end
$var wire 1 . start $end
$var wire 16 6 x [15:0] $end
$var wire 16 7 y [15:0] $end
$var reg 1 8 busy_flag $end
$var reg 32 9 times [31:0] $end
$var reg 32 : x_reg [31:0] $end
$var reg 32 ; x_reg_double [31:0] $end
$var reg 16 < x_reg_double_temp [15:0] $end
$var reg 32 = x_reg_neg [31:0] $end
$var reg 32 > x_reg_neg_double [31:0] $end
$var reg 16 ? x_reg_neg_double_temp [15:0] $end
$var reg 17 @ y_reg [0:16] $end
$var reg 32 A z [31:0] $end
$var reg 32 B z_temp [31:0] $end
$upscope $end
$upscope $end
$enddefinitions $end
#0
$dumpvars
b0 B
bx A
b0 @
bx ?
b0 >
b0 =
bx <
b0 ;
b0 :
b0 9
08
bx 7
bx 6
bx 5
bx 4
bx 3
x2
x1
bx 0
bx /
x.
x-
x,
x+
0*
0)
0(
0'
x&
x%
x$
bx #
x"
x!
$end
#5000
0!
0"
0+
0,
0-
0.
01
b0 /
0%
0&
0$
b0 0
b0 3
b0 6
b0 4
b0 7
02
b1000 5
1(
#10000
0(
#12000
1*
1)
#15000
1+
1(
#20000
0(
#25000
1!
1,
1(
#30000
0(
#35000
0!
11
1-
1(
#40000
0(
#45000
1$
b1 0
1(
#50000
0(
#55000
b101 4
b101 7
b110 3
b110 6
0$
b10 0
1.
1(
#60000
0(
#65000
0.
b11 0
b0 3
b0 6
b0 4
b0 7
1'
18
b1010 @
b11111111111110100000000000000000 =
b1100000000000000000 :
b11111111111101000000000000000000 >
b11000000000000000000 ;
b1111111111110100 ?
b1100 <
1(
#70000
0(
#75000
b1 9
b1 @
b100 0
1(
#80000
0(
#85000
b101 0
b10 9
b0 @
b11000000000000000 B
1(
#90000
0(
#95000
b11 9
b110000000000000 B
b110 0
1(
#100000
0(
#105000
b111 0
b100 9
b1100000000000 B
1(
#110000
0(
#115000
b101 9
b11000000000 B
b1000 0
1(
#120000
0(
#125000
b1001 0
b110 9
b110000000 B
1(
#130000
0(
#135000
b111 9
b1100000 B
b1010 0
1(
#140000
0(
#145000
b1011 0
b1000 9
b11000 B
1(
#150000
0(
#155000
b1001 9
1&
b1100 0
1(
#160000
0(
#165000
1%
0&
b1101 0
x2
b1010 9
0'
08
b11000 #
b11000 A
1(
#170000
0(
#175000
0%
b0 0
b1 /
1(
#180000
0(
#185000
1$
b1 0
1(
#190000
0(
#195000
b101 4
b101 7
b1111111111111010 3
b1111111111111010 6
0$
b10 0
1.
1(
#200000
0(
#205000
0.
b11 0
b0 3
b0 6
b0 4
b0 7
b0 B
b0 9
1'
18
b1010 @
b1100000000000000000 =
b11111111111110100000000000000000 :
b11000000000000000000 >
b11111111111101000000000000000000 ;
b1100 ?
b1111111111110100 <
1(
#210000
0(
#212000
0*
#215000
b1 9
b1 @
b100 0
0+
1(
#220000
0(
#225000
0,
b101 0
b10 9
b0 @
b11111111111111101000000000000000 B
1(
#230000
0(
#235000
b11 9
b11111111111111111010000000000000 B
b110 0
0-
1(
#240000
0(
#245000
b111 0
b100 9
b11111111111111111110100000000000 B
1(
#250000
0(
#255000
b101 9
b11111111111111111111101000000000 B
b1000 0
1(
#260000
0(
#265000
b1001 0
b110 9
b11111111111111111111111010000000 B
1(
#270000
0(
#275000
b111 9
b11111111111111111111111110100000 B
b1010 0
1(
#280000
0(
#285000
b1011 0
b1000 9
b11111111111111111111111111101000 B
1(
#290000
0(
#295000
b1001 9
1&
b1100 0
1(
#300000
0(
#305000
1%
0&
b1101 0
12
b1010 9
0'
08
b11111111111111111111111111101000 #
b11111111111111111111111111101000 A
1(
#310000
0(
#315000
0%
b0 0
b10 /
1(
