lab3/booth/booth.v
module booth (
    input  wire        clk  ,
	input  wire        rst_n,
	input  wire [15:0] x    ,
	input  wire [15:0] y    ,
	input  wire        start,
	output reg  [31:0] z    ,
	output wire        busy 
);

//double signed bit
reg [31:0]	x_reg;
reg [31:0]	x_reg_neg;
reg [0:16]	y_reg;
reg [31:0]	z_temp;

//Whether the x_reg or y_reg has been assigned.
reg			busy_flag;
reg	[31:0]		times;

assign busy = busy_flag;

//Initialize and assign the regs
always @(posedge clk or negedge rst_n) begin
	if(~rst_n) begin
		x_reg <= 0;
		x_reg_neg <= 0;
		y_reg <= {16'h0000,1'b0};
		busy_flag <= 0;
	end

	else if(start) begin
		x_reg <= {x,16'h0000};
		x_reg_neg <= (~x + 1) << 16;
		y_reg <= {y,1'b0};
		busy_flag <= 1;
	end
end


//Start computing
always @(posedge clk or negedge rst_n) begin
	if(~rst_n) begin
		times <= 0;
		z_temp <= 0;
	end
	if(start)	begin
		times <= 0;
		z_temp <= 0;
	end
	if(busy_flag) begin
		if(times >= 16) begin
			z <= z_temp;
			busy_flag <= 0;
		end

		else if(y_reg[15] == 0 & y_reg[16] == 0) begin
			z_temp <= {z_temp[31],z_temp[31:1]} ;
		end
		else if(y_reg[15] == 0 & y_reg[16] == 1) begin
			z_temp = z_temp + x_reg;
			z_temp = {z_temp[31], z_temp[31:1]};
		end
		else if(y_reg[15] == 1 & y_reg[16] == 0) begin
			z_temp = z_temp +x_reg_neg;
			z_temp = {z_temp[31], z_temp[31:1]};
		end
		else if(y_reg[15] == 1 & y_reg[16] == 1) begin
			z_temp <= {z_temp[31],z_temp[31:1]};
		end
		else begin
			busy_flag <= 0;
		end

		y_reg <= y_reg >>1;
		times <= times + 1;
	end
end



endmodule

lab3/booth/testbench.v
`timescale 1ns/1ps

module testbench(
);

reg clk  ;
reg rst_n;
reg start; 
wire busy ;

reg  [15:0] x;
reg  [15:0] y;
wire [31:0] z;

reg        wrong        ;
reg [31:0] result [8:0] ;

initial begin
	$dumpfile("booth.vcd");
	$dumpvars(0,testbench);
    clk = 0;
    rst_n = 0;
    start = 0;
    #12;
    rst_n = 1;
    start = 1;
    #200
    start = 0;
    #2000;
    $finish;

end

always #5 clk = ~clk;

reg start_ff;
reg start_ff2;
reg start_ff3;
reg start_r_ff;

reg [3:0] test_cnt1  ;
reg [4:0] test_cnt2  ;
reg       test_period;

always @ (posedge clk or negedge rst_n) begin
    if (~rst_n) start_ff <= 1'b0;
    else        start_ff <= start;
end

always @ (posedge clk or negedge rst_n) begin
    if (~rst_n) start_ff2 <= 1'b0;
    else        start_ff2 <= start_ff;
end

always @ (posedge clk or negedge rst_n) begin
    if (~rst_n) start_ff3 <= 1'b0;
    else        start_ff3 <= start_ff2;
end

wire start_r = start_ff2 & ~start_ff3;

always @ (posedge clk or negedge rst_n) begin
    if (~rst_n) start_r_ff <= 1'b0;
    else        start_r_ff <= (test_cnt2 == 5'h01) & test_period;
end

wire test_cnt1_end = (test_cnt1 == 4'h8) & test_cnt2_end;
wire test_cnt2_end = (test_cnt2 == 5'h16);
wire check_point = (test_cnt2 == 5'h15);

always @ (posedge clk or negedge rst_n) begin
    if (~rst_n)             test_period <= 1'b0;
	else if (test_cnt1_end) test_period <= 1'b0;
	else if (start_r)       test_period <= 1'b1;
end

always @ (posedge clk or negedge rst_n) begin
    if (~rst_n)             test_cnt1 <= 4'h0;
	else if (test_cnt1_end) test_cnt1 <= 4'h0;
	else if (test_cnt2_end) test_cnt1 <= test_cnt1 + 4'h1;
end

always @ (posedge clk or negedge rst_n) begin
    if (~rst_n)             test_cnt2 <= 5'h00;
	else if (test_cnt2_end) test_cnt2 <= 5'h00;
	else if (test_period)   test_cnt2 <= test_cnt2 + 5'h01;
end

wire test_cnt2_eq_1 = (test_cnt2 == 5'h01);

always @ (posedge clk or negedge rst_n) begin
    if (~rst_n) x <= 16'h0;
	else if (test_cnt2_eq_1) begin
	    case (test_cnt1)
		    4'h0 : x <= 16'h0006;
			4'h1 : x <= 16'hfffa;
			4'h2 : x <= 16'h0000;
			4'h3 : x <= 16'h1234;
			4'h4 : x <= 16'hf100;
			4'h5 : x <= 16'h8001;
			4'h6 : x <= 16'h7658;
			4'h7 : x <= 16'h04f8;
			4'h8 : x <= 16'h0589;
			default : x <= 16'h0;
		endcase
	end
	else x <= 16'h0;
end

always @ (posedge clk or negedge rst_n) begin
    if (~rst_n) y <= 16'h0;
	else if (test_cnt2_eq_1) begin
	    case (test_cnt1)
		    4'h0 : y <= 16'h0005;
			4'h1 : y <= 16'h0005;
			4'h2 : y <= 16'hff21;
			4'h3 : y <= 16'h1234;
			4'h4 : y <= 16'hf789;
			4'h5 : y <= 16'h6578;
			4'h6 : y <= 16'h0000;
			4'h7 : y <= 16'h1400;
			4'h8 : y <= 16'hc643;
			default : y <= 16'h0;
		endcase
	end
	else y <= 16'h0;
end

integer i;
always @ (posedge clk or negedge rst_n) begin
    if (~rst_n) begin
	    for (i=0;i<=7;i=i+1)
		   result[i] <= 32'h0;
	end
	else begin
		result[0] <= 32'h0000001e;
		result[1] <= 32'hffffffe2;
		result[2] <= 32'h00000000;
		result[3] <= 32'h014B5A90;
		result[4] <= 32'h007EF900;
		result[5] <= 32'hCD446578;
		result[6] <= 32'h00000000;
		result[7] <= 32'h00636000;
		result[8] <= 32'hFEC068DB;
	end
end

always @ (posedge clk or negedge rst_n) begin
    if (~rst_n) wrong <= 1'b0;
	else if (check_point) begin
		wrong <= ~(result[test_cnt1] == z);
    end
end	

always @ (posedge clk) begin
	if (wrong) begin
	    $display("wrong at index %x",test_cnt1);
	    $display("=====================================");
	    $display("Test end!");
        $display("----FAIL!!!");
		$display("x           : %x",x);
		$display("y           : %x",y);
		$display("reference   : %x",result[test_cnt1]);
		$display("test module : %x",z); 
	    $finish;
    end
	else if (test_cnt1_end) begin
	    $display("test %x finished",test_cnt1);
	    $display("====================================");
	    $display("Test end!");
        $display("----PASS!!!");
	    $finish;
    end
end

booth u_booth (
    .clk    (clk       ),
    .rst_n  (rst_n     ),
    .x      (x         ),
    .y      (y         ),
    .start  (start_r_ff),
    .z      (z         ),
    .busy   (busy      )
);

endmodule

lab3/booth/booth.vcd
$date
	Wed May 18 19:48:10 2022
$end
$version
	Icarus Verilog
$end
$timescale
	1ps
$end
$scope module testbench $end
$var wire 1 ! start_r $end
$var wire 1 " test_cnt1_end $end
$var wire 32 # z [31:0] $end
$var wire 1 $ test_cnt2_eq_1 $end
$var wire 1 % test_cnt2_end $end
$var wire 1 & check_point $end
$var wire 1 ' busy $end
$var reg 1 ( clk $end
$var reg 1 ) rst_n $end
$var reg 1 * start $end
$var reg 1 + start_ff $end
$var reg 1 , start_ff2 $end
$var reg 1 - start_ff3 $end
$var reg 1 . start_r_ff $end
$var reg 4 / test_cnt1 [3:0] $end
$var reg 5 0 test_cnt2 [4:0] $end
$var reg 1 1 test_period $end
$var reg 1 2 wrong $end
$var reg 16 3 x [15:0] $end
$var reg 16 4 y [15:0] $end
$var integer 32 5 i [31:0] $end
$scope module u_booth $end
$var wire 1 ' busy $end
$var wire 1 ( clk $end
$var wire 1 ) rst_n $end
$var wire 1 . start $end
$var wire 16 6 x [15:0] $end
$var wire 16 7 y [15:0] $end
$var reg 1 8 busy_flag $end
$var reg 32 9 times [31:0] $end
$var reg 32 : x_reg [31:0] $end
$var reg 32 ; x_reg_neg [31:0] $end
$var reg 17 < y_reg [0:16] $end
$var reg 32 = z [31:0] $end
$var reg 32 > z_temp [31:0] $end
$upscope $end
$upscope $end
$enddefinitions $end
#0
$dumpvars
b0 >
bx =
b0 <
b0 ;
b0 :
b0 9
08
bx 7
bx 6
bx 5
bx 4
bx 3
x2
x1
bx 0
bx /
x.
x-
x,
x+
0*
0)
0(
0'
x&
x%
x$
bx #
x"
x!
$end
#5000
0!
0"
0+
0,
0-
0.
01
b0 /
0%
0&
0$
b0 0
b0 3
b0 6
b0 4
b0 7
02
b1000 5
1(
#10000
0(
#12000
1*
1)
#15000
1+
1(
#20000
0(
#25000
1!
1,
1(
#30000
0(
#35000
0!
11
1-
1(
#40000
0(
#45000
1$
b1 0
1(
#50000
0(
#55000
b101 4
b101 7
b110 3
b110 6
0$
b10 0
1.
1(
#60000
0(
#65000
0.
b11 0
b0 3
b0 6
b0 4
b0 7
1'
18
b1010 <
b11111111111110100000000000000000 ;
b1100000000000000000 :
1(
#70000
0(
#75000
b1 9
b101 <
b100 0
b11111111111111010000000000000000 >
1(
#80000
0(
#85000
b101 0
b10 9
b10 <
b11000000000000000 >
1(
#90000
0(
#95000
b11 9
b1 <
b110 0
b11111111111111011100000000000000 >
1(
#100000
0(
#105000
b111 0
b100 9
b0 <
b11110000000000000 >
1(
#110000
0(
#115000
b101 9
b1111000000000000 >
b1000 0
1(
#120000
0(
#125000
b1001 0
b110 9
b111100000000000 >
1(
#130000
0(
#135000
b111 9
b11110000000000 >
b1010 0
1(
#140000
0(
#145000
b1011 0
b1000 9
b1111000000000 >
1(
#150000
0(
#155000
b1001 9
b111100000000 >
b1100 0
1(
#160000
0(
#165000
b1101 0
b1010 9
b11110000000 >
1(
#170000
0(
#175000
b1011 9
b1111000000 >
b1110 0
1(
#180000
0(
#185000
b1111 0
b1100 9
b111100000 >
1(
#190000
0(
#195000
b1101 9
b11110000 >
b10000 0
1(
#200000
0(
#205000
b10001 0
b1110 9
b1111000 >
1(
#210000
0(
#212000
0*
#215000
b1111 9
b111100 >
b10010 0
0+
1(
#220000
0(
#225000
0,
b10011 0
b10000 9
b11110 >
1(
#230000
0(
#235000
b10001 9
0'
08
b11110 #
b11110 =
b10100 0
0-
1(
#240000
0(
#245000
1&
b10101 0
1(
#250000
0(
#255000
1%
0&
b10110 0
1(
#260000
0(
#265000
b1 /
0%
b0 0
1(
#270000
0(
#275000
1$
b1 0
1(
#280000
0(
#285000
1.
0$
b10 0
b1111111111111010 3
b1111111111111010 6
b101 4
b101 7
1(
#290000
0(
#295000
1'
18
b1010 <
b1100000000000000000 ;
b11111111111110100000000000000000 :
b0 >
b0 9
b0 4
b0 7
b0 3
b0 6
b11 0
0.
1(
#300000
0(
#305000
b100 0
b1 9
b101 <
b110000000000000000 >
1(
#310000
0(
#315000
b10 9
b10 <
b101 0
b11111111111111101000000000000000 >
1(
#320000
0(
#325000
b110 0
b11 9
b1 <
b100100000000000000 >
1(
#330000
0(
#335000
b100 9
b0 <
b111 0
b11111111111111100010000000000000 >
1(
#340000
0(
#345000
b1000 0
b101 9
b11111111111111110001000000000000 >
1(
#350000
0(
#355000
b110 9
b11111111111111111000100000000000 >
b1001 0
1(
#360000
0(
#365000
b1010 0
b111 9
b11111111111111111100010000000000 >
1(
#370000
0(
#375000
b1000 9
b11111111111111111110001000000000 >
b1011 0
1(
#380000
0(
#385000
b1100 0
b1001 9
b11111111111111111111000100000000 >
1(
#390000
0(
#395000
b1010 9
b11111111111111111111100010000000 >
b1101 0
1(
#400000
0(
#405000
b1110 0
b1011 9
b11111111111111111111110001000000 >
1(
#410000
0(
#415000
b1100 9
b11111111111111111111111000100000 >
b1111 0
1(
#420000
0(
#425000
b10000 0
b1101 9
b11111111111111111111111100010000 >
1(
#430000
0(
#435000
b1110 9
b11111111111111111111111110001000 >
b10001 0
1(
#440000
0(
#445000
b10010 0
b1111 9
b11111111111111111111111111000100 >
1(
#450000
0(
#455000
b10000 9
b11111111111111111111111111100010 >
b10011 0
1(
#460000
0(
#465000
b10100 0
b10001 9
0'
08
b11111111111111111111111111100010 #
b11111111111111111111111111100010 =
1(
#470000
0(
#475000
1&
b10101 0
1(
#480000
0(
#485000
1%
0&
b10110 0
1(
#490000
0(
#495000
0%
b0 0
b10 /
1(
#500000
0(
#505000
1$
b1 0
1(
#510000
0(
#515000
b1111111100100001 4
b1111111100100001 7
0$
b10 0
1.
1(
#520000
0(
#525000
0.
b11 0
b0 4
b0 7
b0 >
b0 9
1'
18
b11111111001000010 <
b0 ;
b0 :
1(
#530000
0(
#535000
b1 9
b1111111100100001 <
b100 0
1(
#540000
0(
#545000
b101 0
b10 9
b111111110010000 <
1(
#550000
0(
#555000
b11 9
b11111111001000 <
b110 0
1(
#560000
0(
#565000
b111 0
b100 9
b1111111100100 <
1(
#570000
0(
#575000
b101 9
b111111110010 <
b1000 0
1(
#580000
0(
#585000
b1001 0
b110 9
b11111111001 <
1(
#590000
0(
#595000
b111 9
b1111111100 <
b1010 0
1(
#600000
0(
#605000
b1011 0
b1000 9
b111111110 <
1(
#610000
0(
#615000
b1001 9
b11111111 <
b1100 0
1(
#620000
0(
#625000
b1101 0
b1010 9
b1111111 <
1(
#630000
0(
#635000
b1011 9
b111111 <
b1110 0
1(
#640000
0(
#645000
b1111 0
b1100 9
b11111 <
1(
#650000
0(
#655000
b1101 9
b1111 <
b10000 0
1(
#660000
0(
#665000
b10001 0
b1110 9
b111 <
1(
#670000
0(
#675000
b1111 9
b11 <
b10010 0
1(
#680000
0(
#685000
b10011 0
b10000 9
b1 <
1(
#690000
0(
#695000
b10001 9
b0 <
0'
08
b0 #
b0 =
b10100 0
1(
#700000
0(
#705000
1&
b10101 0
1(
#710000
0(
#715000
1%
0&
b10110 0
1(
#720000
0(
#725000
b11 /
0%
b0 0
1(
#730000
0(
#735000
1$
b1 0
1(
#740000
0(
#745000
1.
0$
b10 0
b1001000110100 3
b1001000110100 6
b1001000110100 4
b1001000110100 7
1(
#750000
0(
#755000
1'
18
b10010001101000 <
b11101101110011000000000000000000 ;
b10010001101000000000000000000 :
b0 9
b0 4
b0 7
b0 3
b0 6
b11 0
0.
1(
#760000
0(
#765000
b100 0
b1 9
b1001000110100 <
1(
#770000
0(
#775000
b10 9
b100100011010 <
b101 0
1(
#780000
0(
#785000
b110 0
b11 9
b10010001101 <
b11110110111001100000000000000000 >
1(
#790000
0(
#795000
b100 9
b1001000110 <
b111 0
b100100011010000000000000000 >
1(
#800000
0(
#805000
b1000 0
b101 9
b100100011 <
b11111001001011001000000000000000 >
1(
#810000
0(
#815000
b110 9
b10010001 <
b11111100100101100100000000000000 >
b1001 0
1(
#820000
0(
#825000
b1010 0
b111 9
b1001000 <
b111011001010010000000000000 >
1(
#830000
0(
#835000
b1000 9
b100100 <
b11101100101001000000000000 >
b1011 0
1(
#840000
0(
#845000
b1100 0
b1001 9
b10010 <
b1110110010100100000000000 >
1(
#850000
0(
#855000
b1010 9
b1001 <
b1101 0
b11110111110100101010010000000000 >
1(
#860000
0(
#865000
b1110 0
b1011 9
b100 <
b101000000110101001000000000 >
1(
#870000
0(
#875000
b1100 9
b10 <
b10100000011010100100000000 >
b1111 0
1(
#880000
0(
#885000
b10000 0
b1101 9
b1 <
b11111000001001101101010010000000 >
1(
#890000
0(
#895000
b1110 9
b0 <
b10001 0
b101001011010110101001000000 >
1(
#900000
0(
#905000
b10010 0
b1111 9
b10100101101011010100100000 >
1(
#910000
0(
#915000
b10000 9
b1010010110101101010010000 >
b10011 0
1(
#920000
0(
#925000
b10100 0
b10001 9
0'
08
b1010010110101101010010000 #
b1010010110101101010010000 =
1(
#930000
0(
#935000
1&
b10101 0
1(
#940000
0(
#945000
1%
0&
b10110 0
1(
#950000
0(
#955000
0%
b0 0
b100 /
1(
#960000
0(
#965000
1$
b1 0
1(
#970000
0(
#975000
b1111011110001001 4
b1111011110001001 7
b1111000100000000 3
b1111000100000000 6
0$
b10 0
1.
1(
#980000
0(
#985000
0.
b11 0
b0 3
b0 6
b0 4
b0 7
b0 >
b0 9
1'
18
b11110111100010010 <
b1111000000000000000000000000 ;
b11110001000000000000000000000000 :
1(
#990000
0(
#995000
b1 9
b1111011110001001 <
b100 0
b111100000000000000000000000 >
1(
#1000000
0(
#1005000
b101 0
b10 9
b111101111000100 <
b11111100010000000000000000000000 >
1(
#1010000
0(
#1015000
b11 9
b11110111100010 <
b11111110001000000000000000000000 >
b110 0
1(
#1020000
0(
#1025000
b111 0
b100 9
b1111011110001 <
b110100100000000000000000000 >
1(
#1030000
0(
#1035000
b101 9
b111101111000 <
b1000 0
b11111011110010000000000000000000 >
1(
#1040000
0(
#1045000
b1001 0
b110 9
b11110111100 <
b11111101111001000000000000000000 >
1(
#1050000
0(
#1055000
b111 9
b1111011110 <
b11111110111100100000000000000000 >
b1010 0
1(
#1060000
0(
#1065000
b1011 0
b1000 9
b111101111 <
b110111110010000000000000000 >
1(
#1070000
0(
#1075000
b1001 9
b11110111 <
b11011111001000000000000000 >
b1100 0
1(
#1080000
0(
#1085000
b1101 0
b1010 9
b1111011 <
b1101111100100000000000000 >
1(
#1090000
0(
#1095000
b1011 9
b111101 <
b110111110010000000000000 >
b1110 0
1(
#1100000
0(
#1105000
b1111 0
b1100 9
b11110 <
b11111000111011111001000000000000 >
1(
#1110000
0(
#1115000
b1101 9
b1111 <
b10000 0
b11111101111100100000000000 >
1(
#1120000
0(
#1125000
b10001 0
b1110 9
b111 <
b1111110111110010000000000 >
1(
#1130000
0(
#1135000
b1111 9
b11 <
b111111011111001000000000 >
b10010 0
1(
#1140000
0(
#1145000
b10011 0
b10000 9
b1 <
b11111101111100100000000 >
1(
#1150000
0(
#1155000
b10001 9
b0 <
0'
08
b11111101111100100000000 #
b11111101111100100000000 =
b10100 0
1(
#1160000
0(
#1165000
1&
b10101 0
1(
#1170000
0(
#1175000
1%
0&
b10110 0
1(
#1180000
0(
#1185000
b101 /
0%
b0 0
1(
#1190000
0(
#1195000
1$
b1 0
1(
#1200000
0(
#1205000
1.
0$
b10 0
b1000000000000001 3
b1000000000000001 6
b110010101111000 4
b110010101111000 7
1(
#1210000
0(
#1215000
1'
18
b1100101011110000 <
b1111111111111110000000000000000 ;
b10000000000000010000000000000000 :
b0 >
b0 9
b0 4
b0 7
b0 3
b0 6
b11 0
0.
1(
#1220000
0(
#1225000
b100 0
b1 9
b110010101111000 <
1(
#1230000
0(
#1235000
b10 9
b11001010111100 <
b101 0
1(
#1240000
0(
#1245000
b110 0
b11 9
b1100101011110 <
1(
#1250000
0(
#1255000
b100 9
b110010101111 <
b111 0
b111111111111111000000000000000 >
1(
#1260000
0(
#1265000
b1000 0
b101 9
b11001010111 <
b11111111111111100000000000000 >
1(
#1270000
0(
#1275000
b110 9
b1100101011 <
b1111111111111110000000000000 >
b1001 0
1(
#1280000
0(
#1285000
b1010 0
b111 9
b110010101 <
b111111111111111000000000000 >
1(
#1290000
0(
#1295000
b1000 9
b11001010 <
b1011 0
b11000100000000000111100000000000 >
1(
#1300000
0(
#1305000
b1100 0
b1001 9
b1100101 <
b100001111111111011110000000000 >
1(
#1310000
0(
#1315000
b1010 9
b110010 <
b1101 0
b11010001000000000101111000000000 >
1(
#1320000
0(
#1325000
b1110 0
b1011 9
b11001 <
b101000011111111010111100000000 >
1(
#1330000
0(
#1335000
b1100 9
b1100 <
b1111 0
b11010100010000000101011110000000 >
1(
#1340000
0(
#1345000
b10000 0
b1101 9
b110 <
b11101010001000000010101111000000 >
1(
#1350000
0(
#1355000
b1110 9
b11 <
b10001 0
b110101000011111001010111100000 >
1(
#1360000
0(
#1365000
b10010 0
b1111 9
b1 <
b11010100001111100101011110000 >
1(
#1370000
0(
#1375000
b10000 9
b0 <
b10011 0
b11001101010001000110010101111000 >
1(
#1380000
0(
#1385000
b10100 0
b10001 9
0'
08
b11001101010001000110010101111000 #
b11001101010001000110010101111000 =
1(
#1390000
0(
#1395000
1&
b10101 0
1(
#1400000
0(
#1405000
1%
0&
b10110 0
1(
#1410000
0(
#1415000
0%
b0 0
b110 /
1(
#1420000
0(
#1425000
1$
b1 0
1(
#1430000
0(
#1435000
b111011001011000 3
b111011001011000 6
0$
b10 0
1.
1(
#1440000
0(
#1445000
0.
b11 0
b0 3
b0 6
b0 >
b0 9
1'
18
b10001001101010000000000000000000 ;
b1110110010110000000000000000000 :
1(
#1450000
0(
#1455000
b1 9
b100 0
1(
#1460000
0(
#1465000
b101 0
b10 9
1(
#1470000
0(
#1475000
b11 9
b110 0
1(
#1480000
0(
#1485000
b111 0
b100 9
1(
#1490000
0(
#1495000
b101 9
b1000 0
1(
#1500000
0(
#1505000
b1001 0
b110 9
1(
#1510000
0(
#1515000
b111 9
b1010 0
1(
#1520000
0(
#1525000
b1011 0
b1000 9
1(
#1530000
0(
#1535000
b1001 9
b1100 0
1(
#1540000
0(
#1545000
b1101 0
b1010 9
1(
#1550000
0(
#1555000
b1011 9
b1110 0
1(
#1560000
0(
#1565000
b1111 0
b1100 9
1(
#1570000
0(
#1575000
b1101 9
b10000 0
1(
#1580000
0(
#1585000
b10001 0
b1110 9
1(
#1590000
0(
#1595000
b1111 9
b10010 0
1(
#1600000
0(
#1605000
b10011 0
b10000 9
1(
#1610000
0(
#1615000
b10001 9
0'
08
b0 #
b0 =
b10100 0
1(
#1620000
0(
#1625000
1&
b10101 0
1(
#1630000
0(
#1635000
1%
0&
b10110 0
1(
#1640000
0(
#1645000
b111 /
0%
b0 0
1(
#1650000
0(
#1655000
1$
b1 0
1(
#1660000
0(
#1665000
1.
0$
b10 0
b10011111000 3
b10011111000 6
b1010000000000 4
b1010000000000 7
1(
#1670000
0(
#1675000
1'
18
b10100000000000 <
b11111011000010000000000000000000 ;
b100111110000000000000000000 :
b0 9
b0 4
b0 7
b0 3
b0 6
b11 0
0.
1(
#1680000
0(
#1685000
b100 0
b1 9
b1010000000000 <
1(
#1690000
0(
#1695000
b10 9
b101000000000 <
b101 0
1(
#1700000
0(
#1705000
b110 0
b11 9
b10100000000 <
1(
#1710000
0(
#1715000
b100 9
b1010000000 <
b111 0
1(
#1720000
0(
#1725000
b1000 0
b101 9
b101000000 <
1(
#1730000
0(
#1735000
b110 9
b10100000 <
b1001 0
1(
#1740000
0(
#1745000
b1010 0
b111 9
b1010000 <
1(
#1750000
0(
#1755000
b1000 9
b101000 <
b1011 0
1(
#1760000
0(
#1765000
b1100 0
b1001 9
b10100 <
1(
#1770000
0(
#1775000
b1010 9
b1010 <
b1101 0
1(
#1780000
0(
#1785000
b1110 0
b1011 9
b101 <
b11111101100001000000000000000000 >
1(
#1790000
0(
#1795000
b1100 9
b10 <
b1111 0
b1001111100000000000000000 >
1(
#1800000
0(
#1805000
b10000 0
b1101 9
b1 <
b11111110001000110000000000000000 >
1(
#1810000
0(
#1815000
b1110 9
b0 <
b10001 0
b1100011011000000000000000 >
1(
#1820000
0(
#1825000
b10010 0
b1111 9
b110001101100000000000000 >
1(
#1830000
0(
#1835000
b10000 9
b11000110110000000000000 >
b10011 0
1(
#1840000
0(
#1845000
b10100 0
b10001 9
0'
08
b11000110110000000000000 #
b11000110110000000000000 =
1(
#1850000
0(
#1855000
1&
b10101 0
1(
#1860000
0(
#1865000
1%
0&
b10110 0
1(
#1870000
0(
#1875000
0%
b0 0
b1000 /
1(
#1880000
0(
#1885000
1$
b1 0
1(
#1890000
0(
#1895000
b1100011001000011 4
b1100011001000011 7
b10110001001 3
b10110001001 6
0$
b10 0
1.
1(
#1900000
0(
#1905000
0.
b11 0
b0 3
b0 6
b0 4
b0 7
b0 >
b0 9
1'
18
b11000110010000110 <
b11111010011101110000000000000000 ;
b101100010010000000000000000 :
1(
#1910000
0(
#1915000
b1 9
b1100011001000011 <
b100 0
b11111101001110111000000000000000 >
1(
#1920000
0(
#1925000
b101 0
b10 9
b110001100100001 <
b11111110100111011100000000000000 >
1(
#1930000
0(
#1935000
b11 9
b11000110010000 <
b110 0
b10000100110110000000000000 >
1(
#1940000
0(
#1945000
b111 0
b100 9
b1100011001000 <
b1000010011011000000000000 >
1(
#1950000
0(
#1955000
b101 9
b110001100100 <
b100001001101100000000000 >
b1000 0
1(
#1960000
0(
#1965000
b1001 0
b110 9
b11000110010 <
b10000100110110000000000 >
1(
#1970000
0(
#1975000
b111 9
b1100011001 <
b1010 0
b11111101010111001011011000000000 >
1(
#1980000
0(
#1985000
b1011 0
b1000 9
b110001100 <
b1011100101101101100000000 >
1(
#1990000
0(
#1995000
b1001 9
b11000110 <
b101110010110110110000000 >
b1100 0
1(
#2000000
0(
#2005000
b1101 0
b1010 9
b1100011 <
b11111101100110000011011011000000 >
1(
#2010000
0(
#2015000
b1011 9
b110001 <
b11111110110011000001101101100000 >
b1110 0
1(
#2020000
0(
#2025000
b1111 0
b1100 9
b11000 <
b10001010101000110110110000 >
1(
#2030000
0(
#2035000
b1101 9
b1100 <
b1000101010100011011011000 >
b10000 0
1(
#2040000
0(
#2045000
b10001 0
b1110 9
b110 <
b100010101010001101101100 >
1(
#2050000
0(
#2055000
b1111 9
b11 <
b10010 0
b11111101100000001101000110110110 >
1(
#2060000
0(
#2065000
b10011 0
b10000 9
b1 <
b11111110110000000110100011011011 >
1(
#2070000
0(
#2075000
b10001 9
b0 <
0'
08
b11111110110000000110100011011011 #
b11111110110000000110100011011011 =
b10100 0
1(
#2080000
0(
#2085000
1&
b10101 0
1(
#2090000
0(
#2095000
1"
1%
0&
b10110 0
1(
#2100000
0(
#2105000
0"
01
b0 /
0%
b0 0
1(
